setup.py
XMLAndJSONSerializer.egg-info/PKG-INFO
XMLAndJSONSerializer.egg-info/SOURCES.txt
XMLAndJSONSerializer.egg-info/dependency_links.txt
XMLAndJSONSerializer.egg-info/requires.txt
XMLAndJSONSerializer.egg-info/top_level.txt
serializers/__init__.py
serializers/base_serializer.py
serializers/constants.py
serializers/dict_serializer.py
serializers/factory.py
serializers/json.py
serializers/xml.py
tests/__init__.py
tests/json_tests.py
tests/test_constants.py
tests/xml_tests.py