Metadata-Version: 2.1
Name: XMLAndJSONSerializer
Version: 0.1.0
Summary: Library for class and function serialization
Author: Uladzislau
Author-email: vladislav2256@gmail.com
Classifier: Intended Audience :: Developers
Classifier: Programming Language :: Python :: 3.10
Classifier: Operating System :: OS Independent
